showImagelib/__init__.py
showImagelib/functions.py
showImagelib-0.1.1.dist-info/METADATA
showImagelib-0.1.1.dist-info/WHEEL
showImagelib-0.1.1.dist-info/top_level.txt
showImagelib-0.1.1.dist-info/RECORD
