Metadata-Version: 2.1
Name: showImagelib
Version: 0.1.1
Summary: FBI function library
Home-page: UNKNOWN
Author: Raymond
License: UWO
Platform: UNKNOWN
